{
  "project_info": {
    "project_number": "519711568370",
    "firebase_url": "https://checkers-mobile-default-rtdb.firebaseio.com",
    "project_id": "checkers-mobile",
    "storage_bucket": "checkers-mobile.appspot.com"
  },
  "client": [
    {
      "client_info": {
        "mobilesdk_app_id": "1:519711568370:android:a81781eadf661916387b6b",
        "android_client_info": {
          "package_name": "com.stax3.Checkers"
        }
      },
      "oauth_client": [
        {
          "client_id": "519711568370-793bme6cem8qic77sf549m59t4a28i48.apps.googleusercontent.com",
          "client_type": 3
        }
      ],
      "api_key": [
        {
          "current_key": "AIzaSyDOQFJ5bloVUX93Ik_ZUVdBw373XfqoloM"
        }
      ],
      "services": {
        "appinvite_service": {
          "other_platform_oauth_client": [
            {
              "client_id": "519711568370-793bme6cem8qic77sf549m59t4a28i48.apps.googleusercontent.com",
              "client_type": 3
            }
          ]
        }
      }
    }
  ],
  "configuration_version": "1"
}